pynotion/__init__.py
pynotion/client.py
pynotion/endpoints/__init__.py
pynotion/endpoints/base.py
pynotion/endpoints/blocks.py
pynotion/endpoints/comments.py
pynotion/endpoints/databases.py
pynotion/endpoints/pages.py
pynotion/endpoints/search.py
pynotion/endpoints/users.py
pynotion/enums.py
pynotion/exceptions.py
pynotion/schemas/__init__.py
pynotion/schemas/base.py
pynotion/schemas/block.py
pynotion/schemas/comment.py
pynotion/schemas/common.py
pynotion/schemas/database.py
pynotion/schemas/page.py
pynotion/schemas/property_item.py
pynotion/schemas/response.py
pynotion/schemas/user.py
pynotion/types.py
pynotionapi-1.0.2.dist-info/LICENSE
pynotionapi-1.0.2.dist-info/METADATA
pynotionapi-1.0.2.dist-info/WHEEL
pynotionapi-1.0.2.dist-info/RECORD
